otta/__init__.py
otta/fail.py
otta/utils.py
otta/validate.py
otta-1.0.dist-info/METADATA
otta-1.0.dist-info/RECORD
otta-1.0.dist-info/WHEEL
otta-1.0.dist-info/entry_points.txt
otta-1.0.dist-info/top_level.txt
